.gitignore
.travis.yml
CONTRIBUTING.md
LICENSE.txt
MANIFEST.in
Makefile
README.md
manage.py
requirements.txt
setup.py
cmsplugin_collapse/__init__.py
cmsplugin_collapse/cms_plugins.py
cmsplugin_collapse/models.py
cmsplugin_collapse/tests.py
cmsplugin_collapse.egg-info/PKG-INFO
cmsplugin_collapse.egg-info/SOURCES.txt
cmsplugin_collapse.egg-info/dependency_links.txt
cmsplugin_collapse.egg-info/not-zip-safe
cmsplugin_collapse.egg-info/requires.txt
cmsplugin_collapse.egg-info/top_level.txt
cmsplugin_collapse/migrations/0001_initial.py
cmsplugin_collapse/migrations/0002_auto_20160210_0651.py
cmsplugin_collapse/migrations/0003_auto_20160210_0656.py
cmsplugin_collapse/migrations/0004_update_related_name.py
cmsplugin_collapse/migrations/__init__.py
cmsplugin_collapse/south_migrations/0001_initial.py
cmsplugin_collapse/south_migrations/__init__.py
cmsplugin_collapse/templates/cmsplugin_collapse/accordioncollapsible.html
cmsplugin_collapse/templates/cmsplugin_collapse/accordionheader.html
tests/__init__.py
tests/settings.py